procstream/__init__.py
procstream/process/__init__.py
procstream/process/process_template.py
procstream/sink/__init__.py
procstream/sink/data_sink.py
procstream/sink/elasticsearch_sink.py
procstream/source/__init__.py
procstream/source/source.py
procstream/source/source_file.py
procstream/source/source_twitter.py
procestream_kafka_python-0.8.0.dist-info/LICENSE
procestream_kafka_python-0.8.0.dist-info/METADATA
procestream_kafka_python-0.8.0.dist-info/WHEEL
procestream_kafka_python-0.8.0.dist-info/top_level.txt
procestream_kafka_python-0.8.0.dist-info/RECORD
